{
 "size": 2988,
 "price": {
  "average": 8219.564257028112,
  "lower": 1300.0,
  "upper": 180000.0,
  "middle": 7900.0
 },
 "price_square": {
  "average": 106.62569398548871,
  "lower": 13.378523011059578,
  "upper": 526.3157894736842,
  "middle": 92.46327638693516
 },
 "room_1": {
  "size": 944,
  "average": 5422.697033898305,
  "lower": 1300.0,
  "upper": 25000.0,
  "middle": 4300.0
 },
 "room_2": {
  "size": 1282,
  "average": 7185.658346333853,
  "lower": 1500.0,
  "upper": 50000.0,
  "middle": 3850.0
 },
 "room_3": {
  "size": 597,
  "average": 10721.219430485762,
  "lower": 1500.0,
  "upper": 90000.0,
  "middle": 15000.0
 },
 "North": {
  "size": 668,
  "price_square_average": 100.7809259577408
 },
 "South": {
  "size": 2830,
  "price_square_average": 105.26093814742816
 },
 "West": {
  "size": 192,
  "price_square_average": 130.155659654603
 },
 "East": {
  "size": 278,
  "price_square_average": 121.50162978366745
 },
 "plates": {
  "size": 167,
  "data": {
   "外高桥": {
    "size": 2,
    "average": 4290.0
   },
   "淞宝": {
    "size": 16,
    "average": 4881.25
   },
   "松江大学城": {
    "size": 45,
    "average": 5188.888888888889
   },
   "川沙": {
    "size": 17,
    "average": 4694.117647058823
   },
   "徐家汇": {
    "size": 82,
    "average": 12636.951219512195
   },
   "海湾": {
    "size": 3,
    "average": 2933.3333333333335
   },
   "高行": {
    "size": 19,
    "average": 7689.473684210527
   },
   "惠南": {
    "size": 16,
    "average": 3081.25
   },
   "杨东": {
    "size": 10,
    "average": 11500.0
   },
   "佘山": {
    "size": 13,
    "average": 7707.692307692308
   },
   "松江新城": {
    "size": 19,
    "average": 5463.1578947368425
   },
   "光新": {
    "size": 7,
    "average": 14142.857142857143
   },
   "长风": {
    "size": 16,
    "average": 6416.875
   },
   "静安新城": {
    "size": 8,
    "average": 8187.5
   },
   "丰庄": {
    "size": 16,
    "average": 5431.25
   },
   "康健": {
    "size": 24,
    "average": 7733.333333333333
   },
   "华新": {
    "size": 15,
    "average": 4846.666666666667
   },
   "张庙": {
    "size": 22,
    "average": 4984.090909090909
   },
   "颛桥": {
    "size": 26,
    "average": 10723.076923076924
   },
   "奉贤金汇": {
    "size": 7,
    "average": 3480.0
   },
   "金虹桥": {
    "size": 17,
    "average": 20170.58823529412
   },
   "董家渡": {
    "size": 2,
    "average": 15000.0
   },
   "罗泾": {
    "size": 2,
    "average": 4300.0
   },
   "金汇": {
    "size": 8,
    "average": 15625.0
   },
   "三林": {
    "size": 29,
    "average": 7094.827586206897
   },
   "梅园": {
    "size": 42,
    "average": 13861.904761904761
   },
   "南桥": {
    "size": 25,
    "average": 2968.0
   },
   "华漕": {
    "size": 46,
    "average": 7339.130434782609
   },
   "七宝": {
    "size": 27,
    "average": 8181.481481481482
   },
   "虹桥": {
    "size": 11,
    "average": 6363.636363636364
   },
   "植物园": {
    "size": 4,
    "average": 6725.0
   },
   "万里": {
    "size": 6,
    "average": 7583.333333333333
   },
   "漕河泾": {
    "size": 2,
    "average": 8500.0
   },
   "老西门": {
    "size": 4,
    "average": 12850.0
   },
   "控江路": {
    "size": 12,
    "average": 5366.666666666667
   },
   "联洋": {
    "size": 4,
    "average": 25375.0
   },
   "真如": {
    "size": 15,
    "average": 8966.666666666666
   },
   "夏阳": {
    "size": 9,
    "average": 4777.777777777777
   },
   "大宁": {
    "size": 44,
    "average": 8986.363636363636
   },
   "杨行": {
    "size": 36,
    "average": 5434.722222222223
   },
   "松江老城": {
    "size": 23,
    "average": 3634.782608695652
   },
   "西藏北路": {
    "size": 36,
    "average": 13875.0
   },
   "南码头": {
    "size": 15,
    "average": 5786.666666666667
   },
   "徐泾": {
    "size": 55,
    "average": 10981.6
   },
   "航华": {
    "size": 6,
    "average": 6250.0
   },
   "建国西路": {
    "size": 8,
    "average": 6500.0
   },
   "莘庄南广场": {
    "size": 27,
    "average": 7303.7037037037035
   },
   "新天地": {
    "size": 10,
    "average": 18160.0
   },
   "源深": {
    "size": 11,
    "average": 12963.636363636364
   },
   "陆家嘴": {
    "size": 30,
    "average": 14165.0
   },
   "杨思前滩": {
    "size": 32,
    "average": 9234.375
   },
   "新成路": {
    "size": 1,
    "average": 2800.0
   },
   "鲁迅公园": {
    "size": 7,
    "average": 7928.571428571428
   },
   "碧云": {
    "size": 8,
    "average": 18974.875
   },
   "彭浦": {
    "size": 36,
    "average": 4666.666666666667
   },
   "永和": {
    "size": 5,
    "average": 4380.0
   },
   "不夜城": {
    "size": 20,
    "average": 9500.0
   },
   "塘桥": {
    "size": 19,
    "average": 12478.947368421053
   },
   "朱家角": {
    "size": 7,
    "average": 7157.142857142857
   },
   "武宁": {
    "size": 33,
    "average": 9422.727272727272
   },
   "北外滩": {
    "size": 14,
    "average": 7414.285714285715
   },
   "真光": {
    "size": 6,
    "average": 6033.333333333333
   },
   "西郊": {
    "size": 6,
    "average": 7033.333333333333
   },
   "吴泾": {
    "size": 19,
    "average": 4142.105263157895
   },
   "阳城": {
    "size": 12,
    "average": 5816.666666666667
   },
   "闸北公园": {
    "size": 7,
    "average": 5628.571428571428
   },
   "淞南": {
    "size": 11,
    "average": 5500.0
   },
   "梅陇": {
    "size": 12,
    "average": 7175.0
   },
   "曹杨": {
    "size": 10,
    "average": 5040.0
   },
   "西渡": {
    "size": 9,
    "average": 2800.0
   },
   "人民广场": {
    "size": 10,
    "average": 14880.0
   },
   "莘庄北广场": {
    "size": 10,
    "average": 5710.0
   },
   "老闵行": {
    "size": 21,
    "average": 4352.380952380952
   },
   "车墩": {
    "size": 1,
    "average": 2000.0
   },
   "长桥": {
    "size": 3,
    "average": 4400.0
   },
   "金桥": {
    "size": 33,
    "average": 6243.939393939394
   },
   "鞍山": {
    "size": 37,
    "average": 5810.810810810811
   },
   "华东理工": {
    "size": 11,
    "average": 5145.454545454545
   },
   "镇宁路": {
    "size": 15,
    "average": 13246.666666666666
   },
   "上海南站": {
    "size": 7,
    "average": 4971.428571428572
   },
   "洋泾": {
    "size": 21,
    "average": 7920.952380952381
   },
   "中山公园": {
    "size": 57,
    "average": 8470.157894736842
   },
   "曹路": {
    "size": 7,
    "average": 5914.285714285715
   },
   "金山": {
    "size": 8,
    "average": 3887.5
   },
   "田林": {
    "size": 10,
    "average": 12420.0
   },
   "大华": {
    "size": 26,
    "average": 7261.538461538462
   },
   "中原": {
    "size": 24,
    "average": 5633.333333333333
   },
   "华泾": {
    "size": 13,
    "average": 9623.076923076924
   },
   "长寿路": {
    "size": 24,
    "average": 11295.833333333334
   },
   "甘泉宜川": {
    "size": 21,
    "average": 4576.190476190476
   },
   "新江湾城": {
    "size": 9,
    "average": 13233.333333333334
   },
   "四川北路": {
    "size": 4,
    "average": 7825.0
   },
   "北蔡": {
    "size": 35,
    "average": 8871.42857142857
   },
   "洞泾": {
    "size": 2,
    "average": 13000.0
   },
   "共富": {
    "size": 9,
    "average": 4933.333333333333
   },
   "世博滨江": {
    "size": 6,
    "average": 32733.333333333332
   },
   "春申": {
    "size": 18,
    "average": 7455.555555555556
   },
   "花木": {
    "size": 6,
    "average": 11900.0
   },
   "南京西路": {
    "size": 48,
    "average": 9986.458333333334
   },
   "九亭": {
    "size": 32,
    "average": 7331.25
   },
   "万体馆": {
    "size": 12,
    "average": 8066.666666666667
   },
   "江湾镇": {
    "size": 17,
    "average": 5822.35294117647
   },
   "仙霞": {
    "size": 13,
    "average": 9023.076923076924
   },
   "泥城镇": {
    "size": 3,
    "average": 2133.3333333333335
   },
   "安亭": {
    "size": 15,
    "average": 4153.333333333333
   },
   "御桥": {
    "size": 6,
    "average": 10166.666666666666
   },
   "曲阳": {
    "size": 22,
    "average": 5804.545454545455
   },
   "共康": {
    "size": 18,
    "average": 6205.555555555556
   },
   "斜土路": {
    "size": 8,
    "average": 10637.5
   },
   "桃浦": {
    "size": 20,
    "average": 5155.0
   },
   "黄浦滨江": {
    "size": 6,
    "average": 35050.0
   },
   "世博": {
    "size": 53,
    "average": 6360.377358490566
   },
   "江宁路": {
    "size": 22,
    "average": 13702.272727272728
   },
   "新场": {
    "size": 4,
    "average": 4025.0
   },
   "顾村": {
    "size": 46,
    "average": 5218.478260869565
   },
   "南翔": {
    "size": 19,
    "average": 6368.421052631579
   },
   "赵巷": {
    "size": 35,
    "average": 8328.0
   },
   "莘闵别墅": {
    "size": 20,
    "average": 7190.0
   },
   "周浦": {
    "size": 22,
    "average": 5404.545454545455
   },
   "古北": {
    "size": 12,
    "average": 19700.0
   },
   "衡山路": {
    "size": 23,
    "average": 8613.04347826087
   },
   "嘉定老城": {
    "size": 5,
    "average": 2830.0
   },
   "新桥": {
    "size": 2,
    "average": 3800.0
   },
   "航头": {
    "size": 6,
    "average": 5033.333333333333
   },
   "嘉定新城": {
    "size": 29,
    "average": 6389.6551724137935
   },
   "菊园新区": {
    "size": 13,
    "average": 3576.923076923077
   },
   "中远两湾城": {
    "size": 2,
    "average": 9750.0
   },
   "周家嘴路": {
    "size": 25,
    "average": 7380.0
   },
   "唐镇": {
    "size": 27,
    "average": 8425.925925925925
   },
   "五角场": {
    "size": 23,
    "average": 6193.478260869565
   },
   "月浦": {
    "size": 8,
    "average": 3712.5
   },
   "上大": {
    "size": 29,
    "average": 6621.379310344828
   },
   "天山": {
    "size": 14,
    "average": 16007.142857142857
   },
   "曹家渡": {
    "size": 37,
    "average": 9051.351351351352
   },
   "大场镇": {
    "size": 8,
    "average": 5050.0
   },
   "静安寺": {
    "size": 24,
    "average": 14275.0
   },
   "北新泾": {
    "size": 26,
    "average": 6334.615384615385
   },
   "临平路": {
    "size": 26,
    "average": 10861.538461538461
   },
   "古美": {
    "size": 19,
    "average": 7400.0
   },
   "高境": {
    "size": 18,
    "average": 6898.055555555556
   },
   "马桥": {
    "size": 2,
    "average": 14250.0
   },
   "五里桥": {
    "size": 14,
    "average": 9899.92857142857
   },
   "黄兴公园": {
    "size": 27,
    "average": 6235.185185185185
   },
   "江桥": {
    "size": 40,
    "average": 5195.0
   },
   "金杨": {
    "size": 32,
    "average": 6265.625
   },
   "康桥": {
    "size": 18,
    "average": 6872.222222222223
   },
   "南京东路": {
    "size": 5,
    "average": 7190.0
   },
   "东外滩": {
    "size": 9,
    "average": 5977.777777777777
   },
   "豫园": {
    "size": 6,
    "average": 12550.0
   },
   "长征": {
    "size": 9,
    "average": 9688.888888888889
   },
   "临港新城": {
    "size": 6,
    "average": 4050.0
   },
   "浦江": {
    "size": 15,
    "average": 6320.0
   },
   "淮海中路": {
    "size": 8,
    "average": 7287.5
   },
   "凉城": {
    "size": 24,
    "average": 5404.166666666667
   },
   "闵浦": {
    "size": 15,
    "average": 4233.333333333333
   },
   "通河": {
    "size": 5,
    "average": 4100.0
   },
   "打浦桥": {
    "size": 16,
    "average": 12153.125
   },
   "潍坊": {
    "size": 29,
    "average": 5929.310344827586
   },
   "龙华": {
    "size": 24,
    "average": 17183.333333333332
   },
   "泗泾": {
    "size": 46,
    "average": 5319.565217391304
   },
   "张江": {
    "size": 34,
    "average": 12208.823529411764
   },
   "罗店": {
    "size": 17,
    "average": 3564.705882352941
   },
   "龙柏": {
    "size": 10,
    "average": 7509.8
   },
   "徐汇滨江": {
    "size": 8,
    "average": 23087.5
   },
   "盈浦": {
    "size": 21,
    "average": 4147.619047619048
   },
   "新华路": {
    "size": 30,
    "average": 8650.0
   },
   "蓬莱公园": {
    "size": 30,
    "average": 11653.333333333334
   }
  }
 }
}